haplophaser/__init__.py
haplophaser/analysis/__init__.py
haplophaser/analysis/comparison.py
haplophaser/analysis/painting.py
haplophaser/analysis/qc.py
haplophaser/analysis/summary.py
haplophaser/assembly/__init__.py
haplophaser/assembly/chimera.py
haplophaser/assembly/mapping.py
haplophaser/assembly/paint.py
haplophaser/assembly/qc.py
haplophaser/assembly/subgenome.py
haplophaser/cli/__init__.py
haplophaser/cli/main.py
haplophaser/cli/viz.py
haplophaser/core/__init__.py
haplophaser/core/config.py
haplophaser/core/filters.py
haplophaser/core/frequencies.py
haplophaser/core/genetic_map.py
haplophaser/core/models.py
haplophaser/expression/__init__.py
haplophaser/expression/bias.py
haplophaser/expression/condition_bias.py
haplophaser/expression/dominance.py
haplophaser/expression/homeolog_expression.py
haplophaser/expression/models.py
haplophaser/expression/report.py
haplophaser/expression/statistics.py
haplophaser/expression/viz.py
haplophaser/io/__init__.py
haplophaser/io/agp.py
haplophaser/io/assembly.py
haplophaser/io/assembly_export.py
haplophaser/io/exports.py
haplophaser/io/expression.py
haplophaser/io/markers.py
haplophaser/io/orthofinder.py
haplophaser/io/populations.py
haplophaser/io/proportions.py
haplophaser/io/synteny.py
haplophaser/io/vcf.py
haplophaser/markers/__init__.py
haplophaser/markers/diagnostic.py
haplophaser/markers/multifounder.py
haplophaser/markers/quality.py
haplophaser/proportion/__init__.py
haplophaser/proportion/blocks.py
haplophaser/proportion/breakpoints.py
haplophaser/proportion/confidence.py
haplophaser/proportion/genotypes.py
haplophaser/proportion/hmm.py
haplophaser/proportion/integrate.py
haplophaser/proportion/results.py
haplophaser/proportion/windows.py
haplophaser/scaffold/__init__.py
haplophaser/scaffold/contig_markers.py
haplophaser/scaffold/continuity.py
haplophaser/scaffold/gaps.py
haplophaser/scaffold/ordering.py
haplophaser/scaffold/orientation.py
haplophaser/scaffold/validation.py
haplophaser/subgenome/__init__.py
haplophaser-0.1.1.dist-info/METADATA
haplophaser-0.1.1.dist-info/WHEEL
haplophaser-0.1.1.dist-info/entry_points.txt
haplophaser-0.1.1.dist-info/licenses/LICENSE
haplophaser-0.1.1.dist-info/RECORD
