Metadata-Version: 2.4
Name: haplophaser
Version: 0.1.1
Summary: Polyploid Haplotype Analysis for Sequenced Eukaryotic References - A comprehensive toolkit for haplotype analysis in complex genomes
Project-URL: Homepage, https://github.com/aseetharam/haplophaser
Project-URL: Documentation, https://github.com/aseetharam/haplophaser#readme
Project-URL: Repository, https://github.com/aseetharam/haplophaser
Project-URL: Issues, https://github.com/aseetharam/haplophaser/issues
Project-URL: Changelog, https://github.com/aseetharam/haplophaser/blob/main/CHANGELOG.md
Author-email: Arun Seetharam <arnstrm@iastate.edu>
Maintainer-email: Arun Seetharam <arnstrm@iastate.edu>
License-Expression: MIT
License-File: LICENSE
Keywords: bioinformatics,expression-bias,genetics,genomics,haplotype,homeolog,maize,paleopolyploid,polyploid,subgenome,wheat
Classifier: Development Status :: 4 - Beta
Classifier: Intended Audience :: Science/Research
Classifier: License :: OSI Approved :: MIT License
Classifier: Operating System :: OS Independent
Classifier: Programming Language :: Python :: 3
Classifier: Programming Language :: Python :: 3.10
Classifier: Programming Language :: Python :: 3.11
Classifier: Programming Language :: Python :: 3.12
Classifier: Topic :: Scientific/Engineering :: Bio-Informatics
Classifier: Typing :: Typed
Requires-Python: >=3.10
Requires-Dist: chromoplot>=0.1.0
Requires-Dist: cyvcf2>=0.30.0
Requires-Dist: numpy>=1.24.0
Requires-Dist: pydantic>=2.0.0
Requires-Dist: pyyaml>=6.0
Requires-Dist: rich>=13.0.0
Requires-Dist: typer>=0.9.0
Provides-Extra: alignment
Requires-Dist: pysam>=0.21.0; extra == 'alignment'
Provides-Extra: all
Requires-Dist: matplotlib>=3.7.0; extra == 'all'
Requires-Dist: pandas>=2.0.0; extra == 'all'
Requires-Dist: pysam>=0.21.0; extra == 'all'
Requires-Dist: scipy>=1.10.0; extra == 'all'
Provides-Extra: dev
Requires-Dist: mypy>=1.0.0; extra == 'dev'
Requires-Dist: pandas>=2.0.0; extra == 'dev'
Requires-Dist: pytest-cov>=4.0.0; extra == 'dev'
Requires-Dist: pytest-timeout>=2.0.0; extra == 'dev'
Requires-Dist: pytest>=7.0.0; extra == 'dev'
Requires-Dist: ruff>=0.1.0; extra == 'dev'
Requires-Dist: scipy>=1.10.0; extra == 'dev'
Provides-Extra: docs
Requires-Dist: mkdocs-material>=9.0.0; extra == 'docs'
Requires-Dist: mkdocs>=1.5.0; extra == 'docs'
Requires-Dist: mkdocstrings[python]>=0.24.0; extra == 'docs'
Provides-Extra: stats
Requires-Dist: pandas>=2.0.0; extra == 'stats'
Requires-Dist: scipy>=1.10.0; extra == 'stats'
Provides-Extra: viz
Requires-Dist: matplotlib>=3.7.0; extra == 'viz'
